LICENSE
README.md
setup.cfg
setup.py
nope/__init__.py
nope/cli/__init__.py
nope/cli/__main__.py
nope/cli/logo.py
nope/cli/main.py
nope/cli/run.py
nope/cli/scan.py
nope/communication/__init__.py
nope/communication/abstractBridgePlugin.py
nope/communication/addLayer.py
nope/communication/bridge.py
nope/communication/getLayer.py
nope/communication/layers/EventCommunicationInterface.py
nope/communication/layers/IoSocketClientLayer.py
nope/communication/layers/__init__.py
nope/communication/layers/abstractLayer.py
nope/communication/layers/mqttLayer.py
nope/decorators/__init__.py
nope/decorators/classes.py
nope/demo/__init__.py
nope/demo/instances/DecoratedHelloWorld.py
nope/demo/instances/HelloWorld.py
nope/demo/instances/__init__.py
nope/demo/plugins/00-load-hello.py
nope/demo/plugins/01-dynamic.py
nope/demo/plugins/02-multiple.py
nope/demo/plugins/03-different-items.py
nope/demo/plugins/04-fix.py
nope/dispatcher/__init__.py
nope/dispatcher/getDispatcher.py
nope/dispatcher/nopeDispatcher.py
nope/dispatcher/baseServices/__init__.py
nope/dispatcher/baseServices/connectivy.py
nope/dispatcher/connectivityManager/__init__.py
nope/dispatcher/connectivityManager/connectivityManager.py
nope/dispatcher/core/__init__.py
nope/dispatcher/core/nopeCore.py
nope/dispatcher/instanceManager/__init__.py
nope/dispatcher/instanceManager/assignmentChecker.py
nope/dispatcher/instanceManager/instanceManager.py
nope/dispatcher/rpcManager/__init__.py
nope/dispatcher/rpcManager/rpcManager.py
nope/dispatcher/rpcManager/selectors.py
nope/eventEmitter/__init__.py
nope/eventEmitter/nopeEventEmitter.py
nope/helpers/__init__.py
nope/helpers/asyncHelpers.py
nope/helpers/dictMethods.py
nope/helpers/dispatcherPathes.py
nope/helpers/dottedDict.py
nope/helpers/emitter.py
nope/helpers/files.py
nope/helpers/hashable.py
nope/helpers/idMethods.py
nope/helpers/importing.py
nope/helpers/jsonMethods.py
nope/helpers/listMethods.py
nope/helpers/objectMethods.py
nope/helpers/path.py
nope_py.egg-info/PKG-INFO
nope_py.egg-info/SOURCES.txt
nope_py.egg-info/dependency_links.txt
nope_py.egg-info/entry_points.txt
nope_py.egg-info/requires.txt
nope_py.egg-info/top_level.txt
