Metadata-Version: 2.1
Name: nope-py
Version: 1.7.8rc3
Summary: NOPE-Lib represents the No Programming Environment Library for python.
Home-page: https://github.com/ZeMA-gGmbH/NoPE-PY.git
Author: Martin Karkowski
Author-email: m.karkowski@zema.de
Maintainer: Martin Karkowski
Maintainer-email: m.karkowski@zema.de
Classifier: Operating System :: OS Independent
Classifier: Programming Language :: Python
Classifier: Topic :: Scientific/Engineering
Classifier: Topic :: Software Development :: Libraries :: Python Modules
License-File: LICENSE
